PytorchFS/FS.py
PytorchFS/__init__.py
PytorchFS/util.py
PytorchFS-1.2.1.dist-info/METADATA
PytorchFS-1.2.1.dist-info/WHEEL
PytorchFS-1.2.1.dist-info/top_level.txt
PytorchFS-1.2.1.dist-info/RECORD
